tutor_contrib_celery-20.0.0.dist-info/licenses/LICENSE.txt
tutorcelery/__about__.py
tutorcelery/__init__.py
tutorcelery/hooks.py
tutorcelery/plugin.py
tutorcelery/patches/.gitignore
tutorcelery/patches/caddyfile
tutorcelery/patches/k8s-deployments
tutorcelery/patches/k8s-services
tutorcelery/patches/kustomization-resources
tutorcelery/patches/openedx-cms-production-settings
tutorcelery/patches/openedx-lms-production-settings
tutorcelery/templates/celery/apps/.gitignore
tutorcelery/templates/celery/build/.gitignore
tutorcelery/templates/celery/k8s/keda.yml
tutorcelery/templates/celery/tasks/lms/.gitignore
tutor_contrib_celery-20.0.0.dist-info/METADATA
tutor_contrib_celery-20.0.0.dist-info/WHEEL
tutor_contrib_celery-20.0.0.dist-info/entry_points.txt
tutor_contrib_celery-20.0.0.dist-info/top_level.txt
tutor_contrib_celery-20.0.0.dist-info/RECORD
